py_incharge/__init__.py
py_incharge/client.py
py_incharge-0.2.0.dist-info/METADATA
py_incharge-0.2.0.dist-info/WHEEL
py_incharge-0.2.0.dist-info/top_level.txt
py_incharge-0.2.0.dist-info/RECORD
