Metadata-Version: 2.4
Name: py-incharge
Version: 0.2.0
Summary: A Python package for remotely controlling Vattenfall EV charging stations
Author-email: Bram <b.dewit@applyai.nl>
Maintainer-email: Bram <b.dewit@applyai.nl>
License-Expression: MIT
Keywords: vattenfall,incharge,ev,charger,electric,vehicle,remote,control,websocket
Classifier: Development Status :: 3 - Alpha
Classifier: Intended Audience :: Developers
Classifier: Topic :: Software Development :: Libraries :: Python Modules
Classifier: Topic :: System :: Hardware :: Hardware Drivers
Classifier: Programming Language :: Python :: 3
Classifier: Programming Language :: Python :: 3.8
Classifier: Programming Language :: Python :: 3.9
Classifier: Programming Language :: Python :: 3.10
Classifier: Programming Language :: Python :: 3.11
Classifier: Programming Language :: Python :: 3.12
Classifier: Operating System :: OS Independent
Requires-Python: >=3.8
Requires-Dist: requests>=2.32.4
Requires-Dist: websocket-client>=1.8.0
Provides-Extra: dev
Requires-Dist: ruff; extra == "dev"
Requires-Dist: pyright; extra == "dev"
